timidity/__init__.py
timidity/__main__.py
timidity/parser.py
timidity/player.py
timidity/skips.py
timidity/util.py
timidity-0.1.2.dist-info/LICENSE
timidity-0.1.2.dist-info/METADATA
timidity-0.1.2.dist-info/WHEEL
timidity-0.1.2.dist-info/top_level.txt
timidity-0.1.2.dist-info/RECORD
