Metadata-Version: 2.1
Name: timidity
Version: 0.1.2
Summary: A lightweight Python MIDI player
Home-page: https://github.com/JinayJain/timidity
Author: Jinay Jain
License: UNKNOWN
Platform: UNKNOWN
